duckducknow.py
setup.py
duckducknow.egg-info/PKG-INFO
duckducknow.egg-info/SOURCES.txt
duckducknow.egg-info/dependency_links.txt
duckducknow.egg-info/entry_points.txt
duckducknow.egg-info/top_level.txt