Metadata-Version: 1.0
Name: duckducknow
Version: 0.1
Summary: Search DuckDuckGo right from your terminal
Home-page: https://github.com/dhamaniasad/duckducknow
Author: Asad Dhamani
Author-email: dhamaniasad+code@gmail.com
License: Unlicense
Platform: UNKNOWN
